krono/__init__.py
krono/main.py
krono-0.1.7.dist-info/entry_points.txt
krono-0.1.7.dist-info/WHEEL
krono-0.1.7.dist-info/METADATA
krono-0.1.7.dist-info/RECORD
