Metadata-Version: 2.1
Name: krono
Version: 0.1.7
Summary: Aplicativo de linha de comando para rastrear o tempo de trabalho
Author: rafaelmatsumoto
Author-email: rafael.matsumoto43@catolicasc.edu.br
Requires-Python: >=3.8,<4.0
Classifier: Programming Language :: Python :: 3
Classifier: Programming Language :: Python :: 3.8
Classifier: Programming Language :: Python :: 3.9
Requires-Dist: pandas (>=1.3.3,<2.0.0)
Requires-Dist: typer (>=0.4.0,<0.5.0)
